<?xml version="1.0"?>
<TblDescription BinaryFilePath="general_results.bin" SummFilePath="general_results.summ" Caption="General results">
  <Column Name="t (s)" Role="argument" Units="s"/>
  <Column Name="RelTol (%)" Role="model_param"/>
  <Column Name="T (K)" Role="model_param"/>
  <Column Name="P (atm)" Role="model_param"/>
  <Column Name="H (J/g)" Role="model_param"/>
  <Column Name="U (J/g)" Role="model_param"/>
  <Column Name="F (J/g)" Role="model_param"/>
  <Column Name="Ro (g/cm3)" Role="model_param"/>
  <Column Name="Mu (g/mole)" Role="model_param"/>
  <Column Name="N (1/cm3)" Role="model_param"/>
  <Column Name="Cp (J/mole/K)" Role="model_param"/>
  <Column Name="Cp (kJ/kg/K)" Role="model_param"/>
  <Column Name="Ar/g;NoName;0;no;;;;;;;;;no;;;0;0;;;;;0;0;0;0;;;;;;;;;/" Role="concentration_mass" Link="//Substance[@Name='Ar/g;NoName;0;no;;;;;;;;;no;;;0;0;;;;;0;0;0;0;;;;;;;;;/']"/>
  <Column Name="Ar/g;NoName;0;no;;;;;;;;;no;;;0;0;;;;;0;0;0;0;;;;;;;;;/" Role="concentration_mass_fraction" Link="//Substance[@Name='Ar/g;NoName;0;no;;;;;;;;;no;;;0;0;;;;;0;0;0;0;;;;;;;;;/']"/>
  <Column Name="Ar/g;NoName;0;no;;;;;;;;;no;;;0;0;;;;;0;0;0;0;;;;;;;;;/" Role="concentration_mole_fraction" Link="//Substance[@Name='Ar/g;NoName;0;no;;;;;;;;;no;;;0;0;;;;;0;0;0;0;;;;;;;;;/']"/>
  <Column Name="Ar/g;NoName;0;no;;;;;;;;;no;;;0;0;;;;;0;0;0;0;;;;;;;;;/" Role="concentration" Link="//Substance[@Name='Ar/g;NoName;0;no;;;;;;;;;no;;;0;0;;;;;0;0;0;0;;;;;;;;;/']"/>
  <Column Name="S2/g;NoName;0;no;;;;;;;;;no;;;0;0;;;;;0;0;0;0;;;;;;;;;/" Role="concentration_mass" Link="//Substance[@Name='S2/g;NoName;0;no;;;;;;;;;no;;;0;0;;;;;0;0;0;0;;;;;;;;;/']"/>
  <Column Name="S2/g;NoName;0;no;;;;;;;;;no;;;0;0;;;;;0;0;0;0;;;;;;;;;/" Role="concentration_mass_fraction" Link="//Substance[@Name='S2/g;NoName;0;no;;;;;;;;;no;;;0;0;;;;;0;0;0;0;;;;;;;;;/']"/>
  <Column Name="S2/g;NoName;0;no;;;;;;;;;no;;;0;0;;;;;0;0;0;0;;;;;;;;;/" Role="concentration_mole_fraction" Link="//Substance[@Name='S2/g;NoName;0;no;;;;;;;;;no;;;0;0;;;;;0;0;0;0;;;;;;;;;/']"/>
  <Column Name="S2/g;NoName;0;no;;;;;;;;;no;;;0;0;;;;;0;0;0;0;;;;;;;;;/" Role="concentration" Link="//Substance[@Name='S2/g;NoName;0;no;;;;;;;;;no;;;0;0;;;;;0;0;0;0;;;;;;;;;/']"/>
  <Column Name="S/g;NoName;0;no;;;;;;;;;no;;;0;0;;;;;0;0;0;0;;;;;;;;;/" Role="concentration_mass" Link="//Substance[@Name='S/g;NoName;0;no;;;;;;;;;no;;;0;0;;;;;0;0;0;0;;;;;;;;;/']"/>
  <Column Name="S/g;NoName;0;no;;;;;;;;;no;;;0;0;;;;;0;0;0;0;;;;;;;;;/" Role="concentration_mass_fraction" Link="//Substance[@Name='S/g;NoName;0;no;;;;;;;;;no;;;0;0;;;;;0;0;0;0;;;;;;;;;/']"/>
  <Column Name="S/g;NoName;0;no;;;;;;;;;no;;;0;0;;;;;0;0;0;0;;;;;;;;;/" Role="concentration_mole_fraction" Link="//Substance[@Name='S/g;NoName;0;no;;;;;;;;;no;;;0;0;;;;;0;0;0;0;;;;;;;;;/']"/>
  <Column Name="S/g;NoName;0;no;;;;;;;;;no;;;0;0;;;;;0;0;0;0;;;;;;;;;/" Role="concentration" Link="//Substance[@Name='S/g;NoName;0;no;;;;;;;;;no;;;0;0;;;;;0;0;0;0;;;;;;;;;/']"/>
  <Column Name="H2/g;NoName;0;no;;;;;;;;;no;;;0;0;;;;;0;0;0;0;;;;;;;;;/" Role="concentration_mass" Link="//Substance[@Name='H2/g;NoName;0;no;;;;;;;;;no;;;0;0;;;;;0;0;0;0;;;;;;;;;/']"/>
  <Column Name="H2/g;NoName;0;no;;;;;;;;;no;;;0;0;;;;;0;0;0;0;;;;;;;;;/" Role="concentration_mass_fraction" Link="//Substance[@Name='H2/g;NoName;0;no;;;;;;;;;no;;;0;0;;;;;0;0;0;0;;;;;;;;;/']"/>
  <Column Name="H2/g;NoName;0;no;;;;;;;;;no;;;0;0;;;;;0;0;0;0;;;;;;;;;/" Role="concentration_mole_fraction" Link="//Substance[@Name='H2/g;NoName;0;no;;;;;;;;;no;;;0;0;;;;;0;0;0;0;;;;;;;;;/']"/>
  <Column Name="H2/g;NoName;0;no;;;;;;;;;no;;;0;0;;;;;0;0;0;0;;;;;;;;;/" Role="concentration" Link="//Substance[@Name='H2/g;NoName;0;no;;;;;;;;;no;;;0;0;;;;;0;0;0;0;;;;;;;;;/']"/>
  <Column Name="H2S/g;NoName;0;no;;;;;;;;;no;;;0;0;;;;;0;0;0;0;;;;;;;;;/" Role="concentration_mass" Link="//Substance[@Name='H2S/g;NoName;0;no;;;;;;;;;no;;;0;0;;;;;0;0;0;0;;;;;;;;;/']"/>
  <Column Name="H2S/g;NoName;0;no;;;;;;;;;no;;;0;0;;;;;0;0;0;0;;;;;;;;;/" Role="concentration_mass_fraction" Link="//Substance[@Name='H2S/g;NoName;0;no;;;;;;;;;no;;;0;0;;;;;0;0;0;0;;;;;;;;;/']"/>
  <Column Name="H2S/g;NoName;0;no;;;;;;;;;no;;;0;0;;;;;0;0;0;0;;;;;;;;;/" Role="concentration_mole_fraction" Link="//Substance[@Name='H2S/g;NoName;0;no;;;;;;;;;no;;;0;0;;;;;0;0;0;0;;;;;;;;;/']"/>
  <Column Name="H2S/g;NoName;0;no;;;;;;;;;no;;;0;0;;;;;0;0;0;0;;;;;;;;;/" Role="concentration" Link="//Substance[@Name='H2S/g;NoName;0;no;;;;;;;;;no;;;0;0;;;;;0;0;0;0;;;;;;;;;/']"/>
  <Column Name="SH/g;NoName;0;no;;;;;;;;;no;;;0;0;;;;;0;0;0;0;;;;;;;;;/" Role="concentration_mass" Link="//Substance[@Name='SH/g;NoName;0;no;;;;;;;;;no;;;0;0;;;;;0;0;0;0;;;;;;;;;/']"/>
  <Column Name="SH/g;NoName;0;no;;;;;;;;;no;;;0;0;;;;;0;0;0;0;;;;;;;;;/" Role="concentration_mass_fraction" Link="//Substance[@Name='SH/g;NoName;0;no;;;;;;;;;no;;;0;0;;;;;0;0;0;0;;;;;;;;;/']"/>
  <Column Name="SH/g;NoName;0;no;;;;;;;;;no;;;0;0;;;;;0;0;0;0;;;;;;;;;/" Role="concentration_mole_fraction" Link="//Substance[@Name='SH/g;NoName;0;no;;;;;;;;;no;;;0;0;;;;;0;0;0;0;;;;;;;;;/']"/>
  <Column Name="SH/g;NoName;0;no;;;;;;;;;no;;;0;0;;;;;0;0;0;0;;;;;;;;;/" Role="concentration" Link="//Substance[@Name='SH/g;NoName;0;no;;;;;;;;;no;;;0;0;;;;;0;0;0;0;;;;;;;;;/']"/>
  <Column Name="H/g;NoName;0;no;;;;;;;;;no;;;0;0;;;;;0;0;0;0;;;;;;;;;/" Role="concentration_mass" Link="//Substance[@Name='H/g;NoName;0;no;;;;;;;;;no;;;0;0;;;;;0;0;0;0;;;;;;;;;/']"/>
  <Column Name="H/g;NoName;0;no;;;;;;;;;no;;;0;0;;;;;0;0;0;0;;;;;;;;;/" Role="concentration_mass_fraction" Link="//Substance[@Name='H/g;NoName;0;no;;;;;;;;;no;;;0;0;;;;;0;0;0;0;;;;;;;;;/']"/>
  <Column Name="H/g;NoName;0;no;;;;;;;;;no;;;0;0;;;;;0;0;0;0;;;;;;;;;/" Role="concentration_mole_fraction" Link="//Substance[@Name='H/g;NoName;0;no;;;;;;;;;no;;;0;0;;;;;0;0;0;0;;;;;;;;;/']"/>
  <Column Name="H/g;NoName;0;no;;;;;;;;;no;;;0;0;;;;;0;0;0;0;;;;;;;;;/" Role="concentration" Link="//Substance[@Name='H/g;NoName;0;no;;;;;;;;;no;;;0;0;;;;;0;0;0;0;;;;;;;;;/']"/>
  <Column Name="S4/g;NoName;0;no;;;;;;;;;no;;;0;0;;;;;0;0;0;0;;;;;;;;;/" Role="concentration_mass" Link="//Substance[@Name='S4/g;NoName;0;no;;;;;;;;;no;;;0;0;;;;;0;0;0;0;;;;;;;;;/']"/>
  <Column Name="S4/g;NoName;0;no;;;;;;;;;no;;;0;0;;;;;0;0;0;0;;;;;;;;;/" Role="concentration_mass_fraction" Link="//Substance[@Name='S4/g;NoName;0;no;;;;;;;;;no;;;0;0;;;;;0;0;0;0;;;;;;;;;/']"/>
  <Column Name="S4/g;NoName;0;no;;;;;;;;;no;;;0;0;;;;;0;0;0;0;;;;;;;;;/" Role="concentration_mole_fraction" Link="//Substance[@Name='S4/g;NoName;0;no;;;;;;;;;no;;;0;0;;;;;0;0;0;0;;;;;;;;;/']"/>
  <Column Name="S4/g;NoName;0;no;;;;;;;;;no;;;0;0;;;;;0;0;0;0;;;;;;;;;/" Role="concentration" Link="//Substance[@Name='S4/g;NoName;0;no;;;;;;;;;no;;;0;0;;;;;0;0;0;0;;;;;;;;;/']"/>
  <Column Name="S/g;NoName;0;no;;;;;;;;;no;;;0;0;;;;;0;0;0;0;;;;;;;;;/+S/g;NoName;0;no;;;;;;;;;no;;;0;0;;;;;0;0;0;0;;;;;;;;;/+M/g;NoName;0;no;;;;;;;;;no;;;0;0;;;;;0;0;0;0;;;;;;;;;/&lt;=&gt;S2/g;NoName;0;no;;;;;;;;;no;;;0;0;;;;;0;0;0;0;;;;;;;;;/+M/g;NoName;0;no;;;;;;;;;no;;;0;0;;;;;0;0;0;0;;;;;;;;;/" Role="rate_direct" Link="//ChemicalProcess[@Name='S/g;NoName;0;no;;;;;;;;;no;;;0;0;;;;;0;0;0;0;;;;;;;;;/+S/g;NoName;0;no;;;;;;;;;no;;;0;0;;;;;0;0;0;0;;;;;;;;;/+M/g;NoName;0;no;;;;;;;;;no;;;0;0;;;;;0;0;0;0;;;;;;;;;/&lt;=&gt;S2/g;NoName;0;no;;;;;;;;;no;;;0;0;;;;;0;0;0;0;;;;;;;;;/+M/g;NoName;0;no;;;;;;;;;no;;;0;0;;;;;0;0;0;0;;;;;;;;;/']"/>
  <Column Name="S/g;NoName;0;no;;;;;;;;;no;;;0;0;;;;;0;0;0;0;;;;;;;;;/+S/g;NoName;0;no;;;;;;;;;no;;;0;0;;;;;0;0;0;0;;;;;;;;;/+M/g;NoName;0;no;;;;;;;;;no;;;0;0;;;;;0;0;0;0;;;;;;;;;/&lt;=&gt;S2/g;NoName;0;no;;;;;;;;;no;;;0;0;;;;;0;0;0;0;;;;;;;;;/+M/g;NoName;0;no;;;;;;;;;no;;;0;0;;;;;0;0;0;0;;;;;;;;;/" Role="rate_reverse" Link="//ChemicalProcess[@Name='S/g;NoName;0;no;;;;;;;;;no;;;0;0;;;;;0;0;0;0;;;;;;;;;/+S/g;NoName;0;no;;;;;;;;;no;;;0;0;;;;;0;0;0;0;;;;;;;;;/+M/g;NoName;0;no;;;;;;;;;no;;;0;0;;;;;0;0;0;0;;;;;;;;;/&lt;=&gt;S2/g;NoName;0;no;;;;;;;;;no;;;0;0;;;;;0;0;0;0;;;;;;;;;/+M/g;NoName;0;no;;;;;;;;;no;;;0;0;;;;;0;0;0;0;;;;;;;;;/']"/>
  <Column Name="S/g;NoName;0;no;;;;;;;;;no;;;0;0;;;;;0;0;0;0;;;;;;;;;/+S/g;NoName;0;no;;;;;;;;;no;;;0;0;;;;;0;0;0;0;;;;;;;;;/+M/g;NoName;0;no;;;;;;;;;no;;;0;0;;;;;0;0;0;0;;;;;;;;;/&lt;=&gt;S2/g;NoName;0;no;;;;;;;;;no;;;0;0;;;;;0;0;0;0;;;;;;;;;/+M/g;NoName;0;no;;;;;;;;;no;;;0;0;;;;;0;0;0;0;;;;;;;;;/" Role="rate" Link="//ChemicalProcess[@Name='S/g;NoName;0;no;;;;;;;;;no;;;0;0;;;;;0;0;0;0;;;;;;;;;/+S/g;NoName;0;no;;;;;;;;;no;;;0;0;;;;;0;0;0;0;;;;;;;;;/+M/g;NoName;0;no;;;;;;;;;no;;;0;0;;;;;0;0;0;0;;;;;;;;;/&lt;=&gt;S2/g;NoName;0;no;;;;;;;;;no;;;0;0;;;;;0;0;0;0;;;;;;;;;/+M/g;NoName;0;no;;;;;;;;;no;;;0;0;;;;;0;0;0;0;;;;;;;;;/']"/>
  <Column Name="S/g;NoName;0;no;;;;;;;;;no;;;0;0;;;;;0;0;0;0;;;;;;;;;/+S/g;NoName;0;no;;;;;;;;;no;;;0;0;;;;;0;0;0;0;;;;;;;;;/+M/g;NoName;0;no;;;;;;;;;no;;;0;0;;;;;0;0;0;0;;;;;;;;;/&lt;=&gt;S2/g;NoName;0;no;;;;;;;;;no;;;0;0;;;;;0;0;0;0;;;;;;;;;/+M/g;NoName;0;no;;;;;;;;;no;;;0;0;;;;;0;0;0;0;;;;;;;;;/" Role="reaction_enthalpy" Link="//ChemicalProcess[@Name='S/g;NoName;0;no;;;;;;;;;no;;;0;0;;;;;0;0;0;0;;;;;;;;;/+S/g;NoName;0;no;;;;;;;;;no;;;0;0;;;;;0;0;0;0;;;;;;;;;/+M/g;NoName;0;no;;;;;;;;;no;;;0;0;;;;;0;0;0;0;;;;;;;;;/&lt;=&gt;S2/g;NoName;0;no;;;;;;;;;no;;;0;0;;;;;0;0;0;0;;;;;;;;;/+M/g;NoName;0;no;;;;;;;;;no;;;0;0;;;;;0;0;0;0;;;;;;;;;/']"/>
  <Column Name="SH/g;NoName;0;no;;;;;;;;;no;;;0;0;;;;;0;0;0;0;;;;;;;;;/+SH/g;NoName;0;no;;;;;;;;;no;;;0;0;;;;;0;0;0;0;;;;;;;;;/&lt;=&gt;H2S/g;NoName;0;no;;;;;;;;;no;;;0;0;;;;;0;0;0;0;;;;;;;;;/+S/g;NoName;0;no;;;;;;;;;no;;;0;0;;;;;0;0;0;0;;;;;;;;;/" Role="rate_direct" Link="//ChemicalProcess[@Name='SH/g;NoName;0;no;;;;;;;;;no;;;0;0;;;;;0;0;0;0;;;;;;;;;/+SH/g;NoName;0;no;;;;;;;;;no;;;0;0;;;;;0;0;0;0;;;;;;;;;/&lt;=&gt;H2S/g;NoName;0;no;;;;;;;;;no;;;0;0;;;;;0;0;0;0;;;;;;;;;/+S/g;NoName;0;no;;;;;;;;;no;;;0;0;;;;;0;0;0;0;;;;;;;;;/']"/>
  <Column Name="SH/g;NoName;0;no;;;;;;;;;no;;;0;0;;;;;0;0;0;0;;;;;;;;;/+SH/g;NoName;0;no;;;;;;;;;no;;;0;0;;;;;0;0;0;0;;;;;;;;;/&lt;=&gt;H2S/g;NoName;0;no;;;;;;;;;no;;;0;0;;;;;0;0;0;0;;;;;;;;;/+S/g;NoName;0;no;;;;;;;;;no;;;0;0;;;;;0;0;0;0;;;;;;;;;/" Role="rate_reverse" Link="//ChemicalProcess[@Name='SH/g;NoName;0;no;;;;;;;;;no;;;0;0;;;;;0;0;0;0;;;;;;;;;/+SH/g;NoName;0;no;;;;;;;;;no;;;0;0;;;;;0;0;0;0;;;;;;;;;/&lt;=&gt;H2S/g;NoName;0;no;;;;;;;;;no;;;0;0;;;;;0;0;0;0;;;;;;;;;/+S/g;NoName;0;no;;;;;;;;;no;;;0;0;;;;;0;0;0;0;;;;;;;;;/']"/>
  <Column Name="SH/g;NoName;0;no;;;;;;;;;no;;;0;0;;;;;0;0;0;0;;;;;;;;;/+SH/g;NoName;0;no;;;;;;;;;no;;;0;0;;;;;0;0;0;0;;;;;;;;;/&lt;=&gt;H2S/g;NoName;0;no;;;;;;;;;no;;;0;0;;;;;0;0;0;0;;;;;;;;;/+S/g;NoName;0;no;;;;;;;;;no;;;0;0;;;;;0;0;0;0;;;;;;;;;/" Role="rate" Link="//ChemicalProcess[@Name='SH/g;NoName;0;no;;;;;;;;;no;;;0;0;;;;;0;0;0;0;;;;;;;;;/+SH/g;NoName;0;no;;;;;;;;;no;;;0;0;;;;;0;0;0;0;;;;;;;;;/&lt;=&gt;H2S/g;NoName;0;no;;;;;;;;;no;;;0;0;;;;;0;0;0;0;;;;;;;;;/+S/g;NoName;0;no;;;;;;;;;no;;;0;0;;;;;0;0;0;0;;;;;;;;;/']"/>
  <Column Name="SH/g;NoName;0;no;;;;;;;;;no;;;0;0;;;;;0;0;0;0;;;;;;;;;/+SH/g;NoName;0;no;;;;;;;;;no;;;0;0;;;;;0;0;0;0;;;;;;;;;/&lt;=&gt;H2S/g;NoName;0;no;;;;;;;;;no;;;0;0;;;;;0;0;0;0;;;;;;;;;/+S/g;NoName;0;no;;;;;;;;;no;;;0;0;;;;;0;0;0;0;;;;;;;;;/" Role="reaction_enthalpy" Link="//ChemicalProcess[@Name='SH/g;NoName;0;no;;;;;;;;;no;;;0;0;;;;;0;0;0;0;;;;;;;;;/+SH/g;NoName;0;no;;;;;;;;;no;;;0;0;;;;;0;0;0;0;;;;;;;;;/&lt;=&gt;H2S/g;NoName;0;no;;;;;;;;;no;;;0;0;;;;;0;0;0;0;;;;;;;;;/+S/g;NoName;0;no;;;;;;;;;no;;;0;0;;;;;0;0;0;0;;;;;;;;;/']"/>
  <Column Name="SH/g;NoName;0;no;;;;;;;;;no;;;0;0;;;;;0;0;0;0;;;;;;;;;/+S/g;NoName;0;no;;;;;;;;;no;;;0;0;;;;;0;0;0;0;;;;;;;;;/&lt;=&gt;H/g;NoName;0;no;;;;;;;;;no;;;0;0;;;;;0;0;0;0;;;;;;;;;/+S2/g;NoName;0;no;;;;;;;;;no;;;0;0;;;;;0;0;0;0;;;;;;;;;/" Role="rate_direct" Link="//ChemicalProcess[@Name='SH/g;NoName;0;no;;;;;;;;;no;;;0;0;;;;;0;0;0;0;;;;;;;;;/+S/g;NoName;0;no;;;;;;;;;no;;;0;0;;;;;0;0;0;0;;;;;;;;;/&lt;=&gt;H/g;NoName;0;no;;;;;;;;;no;;;0;0;;;;;0;0;0;0;;;;;;;;;/+S2/g;NoName;0;no;;;;;;;;;no;;;0;0;;;;;0;0;0;0;;;;;;;;;/']"/>
  <Column Name="SH/g;NoName;0;no;;;;;;;;;no;;;0;0;;;;;0;0;0;0;;;;;;;;;/+S/g;NoName;0;no;;;;;;;;;no;;;0;0;;;;;0;0;0;0;;;;;;;;;/&lt;=&gt;H/g;NoName;0;no;;;;;;;;;no;;;0;0;;;;;0;0;0;0;;;;;;;;;/+S2/g;NoName;0;no;;;;;;;;;no;;;0;0;;;;;0;0;0;0;;;;;;;;;/" Role="rate_reverse" Link="//ChemicalProcess[@Name='SH/g;NoName;0;no;;;;;;;;;no;;;0;0;;;;;0;0;0;0;;;;;;;;;/+S/g;NoName;0;no;;;;;;;;;no;;;0;0;;;;;0;0;0;0;;;;;;;;;/&lt;=&gt;H/g;NoName;0;no;;;;;;;;;no;;;0;0;;;;;0;0;0;0;;;;;;;;;/+S2/g;NoName;0;no;;;;;;;;;no;;;0;0;;;;;0;0;0;0;;;;;;;;;/']"/>
  <Column Name="SH/g;NoName;0;no;;;;;;;;;no;;;0;0;;;;;0;0;0;0;;;;;;;;;/+S/g;NoName;0;no;;;;;;;;;no;;;0;0;;;;;0;0;0;0;;;;;;;;;/&lt;=&gt;H/g;NoName;0;no;;;;;;;;;no;;;0;0;;;;;0;0;0;0;;;;;;;;;/+S2/g;NoName;0;no;;;;;;;;;no;;;0;0;;;;;0;0;0;0;;;;;;;;;/" Role="rate" Link="//ChemicalProcess[@Name='SH/g;NoName;0;no;;;;;;;;;no;;;0;0;;;;;0;0;0;0;;;;;;;;;/+S/g;NoName;0;no;;;;;;;;;no;;;0;0;;;;;0;0;0;0;;;;;;;;;/&lt;=&gt;H/g;NoName;0;no;;;;;;;;;no;;;0;0;;;;;0;0;0;0;;;;;;;;;/+S2/g;NoName;0;no;;;;;;;;;no;;;0;0;;;;;0;0;0;0;;;;;;;;;/']"/>
  <Column Name="SH/g;NoName;0;no;;;;;;;;;no;;;0;0;;;;;0;0;0;0;;;;;;;;;/+S/g;NoName;0;no;;;;;;;;;no;;;0;0;;;;;0;0;0;0;;;;;;;;;/&lt;=&gt;H/g;NoName;0;no;;;;;;;;;no;;;0;0;;;;;0;0;0;0;;;;;;;;;/+S2/g;NoName;0;no;;;;;;;;;no;;;0;0;;;;;0;0;0;0;;;;;;;;;/" Role="reaction_enthalpy" Link="//ChemicalProcess[@Name='SH/g;NoName;0;no;;;;;;;;;no;;;0;0;;;;;0;0;0;0;;;;;;;;;/+S/g;NoName;0;no;;;;;;;;;no;;;0;0;;;;;0;0;0;0;;;;;;;;;/&lt;=&gt;H/g;NoName;0;no;;;;;;;;;no;;;0;0;;;;;0;0;0;0;;;;;;;;;/+S2/g;NoName;0;no;;;;;;;;;no;;;0;0;;;;;0;0;0;0;;;;;;;;;/']"/>
  <Column Name="H/g;NoName;0;no;;;;;;;;;no;;;0;0;;;;;0;0;0;0;;;;;;;;;/+H2S/g;NoName;0;no;;;;;;;;;no;;;0;0;;;;;0;0;0;0;;;;;;;;;/&lt;=&gt;H2/g;NoName;0;no;;;;;;;;;no;;;0;0;;;;;0;0;0;0;;;;;;;;;/+SH/g;NoName;0;no;;;;;;;;;no;;;0;0;;;;;0;0;0;0;;;;;;;;;/" Role="rate_direct" Link="//ChemicalProcess[@Name='H/g;NoName;0;no;;;;;;;;;no;;;0;0;;;;;0;0;0;0;;;;;;;;;/+H2S/g;NoName;0;no;;;;;;;;;no;;;0;0;;;;;0;0;0;0;;;;;;;;;/&lt;=&gt;H2/g;NoName;0;no;;;;;;;;;no;;;0;0;;;;;0;0;0;0;;;;;;;;;/+SH/g;NoName;0;no;;;;;;;;;no;;;0;0;;;;;0;0;0;0;;;;;;;;;/']"/>
  <Column Name="H/g;NoName;0;no;;;;;;;;;no;;;0;0;;;;;0;0;0;0;;;;;;;;;/+H2S/g;NoName;0;no;;;;;;;;;no;;;0;0;;;;;0;0;0;0;;;;;;;;;/&lt;=&gt;H2/g;NoName;0;no;;;;;;;;;no;;;0;0;;;;;0;0;0;0;;;;;;;;;/+SH/g;NoName;0;no;;;;;;;;;no;;;0;0;;;;;0;0;0;0;;;;;;;;;/" Role="rate_reverse" Link="//ChemicalProcess[@Name='H/g;NoName;0;no;;;;;;;;;no;;;0;0;;;;;0;0;0;0;;;;;;;;;/+H2S/g;NoName;0;no;;;;;;;;;no;;;0;0;;;;;0;0;0;0;;;;;;;;;/&lt;=&gt;H2/g;NoName;0;no;;;;;;;;;no;;;0;0;;;;;0;0;0;0;;;;;;;;;/+SH/g;NoName;0;no;;;;;;;;;no;;;0;0;;;;;0;0;0;0;;;;;;;;;/']"/>
  <Column Name="H/g;NoName;0;no;;;;;;;;;no;;;0;0;;;;;0;0;0;0;;;;;;;;;/+H2S/g;NoName;0;no;;;;;;;;;no;;;0;0;;;;;0;0;0;0;;;;;;;;;/&lt;=&gt;H2/g;NoName;0;no;;;;;;;;;no;;;0;0;;;;;0;0;0;0;;;;;;;;;/+SH/g;NoName;0;no;;;;;;;;;no;;;0;0;;;;;0;0;0;0;;;;;;;;;/" Role="rate" Link="//ChemicalProcess[@Name='H/g;NoName;0;no;;;;;;;;;no;;;0;0;;;;;0;0;0;0;;;;;;;;;/+H2S/g;NoName;0;no;;;;;;;;;no;;;0;0;;;;;0;0;0;0;;;;;;;;;/&lt;=&gt;H2/g;NoName;0;no;;;;;;;;;no;;;0;0;;;;;0;0;0;0;;;;;;;;;/+SH/g;NoName;0;no;;;;;;;;;no;;;0;0;;;;;0;0;0;0;;;;;;;;;/']"/>
  <Column Name="H/g;NoName;0;no;;;;;;;;;no;;;0;0;;;;;0;0;0;0;;;;;;;;;/+H2S/g;NoName;0;no;;;;;;;;;no;;;0;0;;;;;0;0;0;0;;;;;;;;;/&lt;=&gt;H2/g;NoName;0;no;;;;;;;;;no;;;0;0;;;;;0;0;0;0;;;;;;;;;/+SH/g;NoName;0;no;;;;;;;;;no;;;0;0;;;;;0;0;0;0;;;;;;;;;/" Role="reaction_enthalpy" Link="//ChemicalProcess[@Name='H/g;NoName;0;no;;;;;;;;;no;;;0;0;;;;;0;0;0;0;;;;;;;;;/+H2S/g;NoName;0;no;;;;;;;;;no;;;0;0;;;;;0;0;0;0;;;;;;;;;/&lt;=&gt;H2/g;NoName;0;no;;;;;;;;;no;;;0;0;;;;;0;0;0;0;;;;;;;;;/+SH/g;NoName;0;no;;;;;;;;;no;;;0;0;;;;;0;0;0;0;;;;;;;;;/']"/>
  <Column Name="H/g;NoName;0;no;;;;;;;;;no;;;0;0;;;;;0;0;0;0;;;;;;;;;/+SH/g;NoName;0;no;;;;;;;;;no;;;0;0;;;;;0;0;0;0;;;;;;;;;/&lt;=&gt;H2/g;NoName;0;no;;;;;;;;;no;;;0;0;;;;;0;0;0;0;;;;;;;;;/+S/g;NoName;0;no;;;;;;;;;no;;;0;0;;;;;0;0;0;0;;;;;;;;;/" Role="rate_direct" Link="//ChemicalProcess[@Name='H/g;NoName;0;no;;;;;;;;;no;;;0;0;;;;;0;0;0;0;;;;;;;;;/+SH/g;NoName;0;no;;;;;;;;;no;;;0;0;;;;;0;0;0;0;;;;;;;;;/&lt;=&gt;H2/g;NoName;0;no;;;;;;;;;no;;;0;0;;;;;0;0;0;0;;;;;;;;;/+S/g;NoName;0;no;;;;;;;;;no;;;0;0;;;;;0;0;0;0;;;;;;;;;/']"/>
  <Column Name="H/g;NoName;0;no;;;;;;;;;no;;;0;0;;;;;0;0;0;0;;;;;;;;;/+SH/g;NoName;0;no;;;;;;;;;no;;;0;0;;;;;0;0;0;0;;;;;;;;;/&lt;=&gt;H2/g;NoName;0;no;;;;;;;;;no;;;0;0;;;;;0;0;0;0;;;;;;;;;/+S/g;NoName;0;no;;;;;;;;;no;;;0;0;;;;;0;0;0;0;;;;;;;;;/" Role="rate_reverse" Link="//ChemicalProcess[@Name='H/g;NoName;0;no;;;;;;;;;no;;;0;0;;;;;0;0;0;0;;;;;;;;;/+SH/g;NoName;0;no;;;;;;;;;no;;;0;0;;;;;0;0;0;0;;;;;;;;;/&lt;=&gt;H2/g;NoName;0;no;;;;;;;;;no;;;0;0;;;;;0;0;0;0;;;;;;;;;/+S/g;NoName;0;no;;;;;;;;;no;;;0;0;;;;;0;0;0;0;;;;;;;;;/']"/>
  <Column Name="H/g;NoName;0;no;;;;;;;;;no;;;0;0;;;;;0;0;0;0;;;;;;;;;/+SH/g;NoName;0;no;;;;;;;;;no;;;0;0;;;;;0;0;0;0;;;;;;;;;/&lt;=&gt;H2/g;NoName;0;no;;;;;;;;;no;;;0;0;;;;;0;0;0;0;;;;;;;;;/+S/g;NoName;0;no;;;;;;;;;no;;;0;0;;;;;0;0;0;0;;;;;;;;;/" Role="rate" Link="//ChemicalProcess[@Name='H/g;NoName;0;no;;;;;;;;;no;;;0;0;;;;;0;0;0;0;;;;;;;;;/+SH/g;NoName;0;no;;;;;;;;;no;;;0;0;;;;;0;0;0;0;;;;;;;;;/&lt;=&gt;H2/g;NoName;0;no;;;;;;;;;no;;;0;0;;;;;0;0;0;0;;;;;;;;;/+S/g;NoName;0;no;;;;;;;;;no;;;0;0;;;;;0;0;0;0;;;;;;;;;/']"/>
  <Column Name="H/g;NoName;0;no;;;;;;;;;no;;;0;0;;;;;0;0;0;0;;;;;;;;;/+SH/g;NoName;0;no;;;;;;;;;no;;;0;0;;;;;0;0;0;0;;;;;;;;;/&lt;=&gt;H2/g;NoName;0;no;;;;;;;;;no;;;0;0;;;;;0;0;0;0;;;;;;;;;/+S/g;NoName;0;no;;;;;;;;;no;;;0;0;;;;;0;0;0;0;;;;;;;;;/" Role="reaction_enthalpy" Link="//ChemicalProcess[@Name='H/g;NoName;0;no;;;;;;;;;no;;;0;0;;;;;0;0;0;0;;;;;;;;;/+SH/g;NoName;0;no;;;;;;;;;no;;;0;0;;;;;0;0;0;0;;;;;;;;;/&lt;=&gt;H2/g;NoName;0;no;;;;;;;;;no;;;0;0;;;;;0;0;0;0;;;;;;;;;/+S/g;NoName;0;no;;;;;;;;;no;;;0;0;;;;;0;0;0;0;;;;;;;;;/']"/>
  <Column Name="H2S/g;NoName;0;no;;;;;;;;;no;;;0;0;;;;;0;0;0;0;;;;;;;;;/+M/g;NoName;0;no;;;;;;;;;no;;;0;0;;;;;0;0;0;0;;;;;;;;;/&lt;=&gt;H/g;NoName;0;no;;;;;;;;;no;;;0;0;;;;;0;0;0;0;;;;;;;;;/+SH/g;NoName;0;no;;;;;;;;;no;;;0;0;;;;;0;0;0;0;;;;;;;;;/+M/g;NoName;0;no;;;;;;;;;no;;;0;0;;;;;0;0;0;0;;;;;;;;;/" Role="rate_direct" Link="//ChemicalProcess[@Name='H2S/g;NoName;0;no;;;;;;;;;no;;;0;0;;;;;0;0;0;0;;;;;;;;;/+M/g;NoName;0;no;;;;;;;;;no;;;0;0;;;;;0;0;0;0;;;;;;;;;/&lt;=&gt;H/g;NoName;0;no;;;;;;;;;no;;;0;0;;;;;0;0;0;0;;;;;;;;;/+SH/g;NoName;0;no;;;;;;;;;no;;;0;0;;;;;0;0;0;0;;;;;;;;;/+M/g;NoName;0;no;;;;;;;;;no;;;0;0;;;;;0;0;0;0;;;;;;;;;/']"/>
  <Column Name="H2S/g;NoName;0;no;;;;;;;;;no;;;0;0;;;;;0;0;0;0;;;;;;;;;/+M/g;NoName;0;no;;;;;;;;;no;;;0;0;;;;;0;0;0;0;;;;;;;;;/&lt;=&gt;H/g;NoName;0;no;;;;;;;;;no;;;0;0;;;;;0;0;0;0;;;;;;;;;/+SH/g;NoName;0;no;;;;;;;;;no;;;0;0;;;;;0;0;0;0;;;;;;;;;/+M/g;NoName;0;no;;;;;;;;;no;;;0;0;;;;;0;0;0;0;;;;;;;;;/" Role="rate_reverse" Link="//ChemicalProcess[@Name='H2S/g;NoName;0;no;;;;;;;;;no;;;0;0;;;;;0;0;0;0;;;;;;;;;/+M/g;NoName;0;no;;;;;;;;;no;;;0;0;;;;;0;0;0;0;;;;;;;;;/&lt;=&gt;H/g;NoName;0;no;;;;;;;;;no;;;0;0;;;;;0;0;0;0;;;;;;;;;/+SH/g;NoName;0;no;;;;;;;;;no;;;0;0;;;;;0;0;0;0;;;;;;;;;/+M/g;NoName;0;no;;;;;;;;;no;;;0;0;;;;;0;0;0;0;;;;;;;;;/']"/>
  <Column Name="H2S/g;NoName;0;no;;;;;;;;;no;;;0;0;;;;;0;0;0;0;;;;;;;;;/+M/g;NoName;0;no;;;;;;;;;no;;;0;0;;;;;0;0;0;0;;;;;;;;;/&lt;=&gt;H/g;NoName;0;no;;;;;;;;;no;;;0;0;;;;;0;0;0;0;;;;;;;;;/+SH/g;NoName;0;no;;;;;;;;;no;;;0;0;;;;;0;0;0;0;;;;;;;;;/+M/g;NoName;0;no;;;;;;;;;no;;;0;0;;;;;0;0;0;0;;;;;;;;;/" Role="rate" Link="//ChemicalProcess[@Name='H2S/g;NoName;0;no;;;;;;;;;no;;;0;0;;;;;0;0;0;0;;;;;;;;;/+M/g;NoName;0;no;;;;;;;;;no;;;0;0;;;;;0;0;0;0;;;;;;;;;/&lt;=&gt;H/g;NoName;0;no;;;;;;;;;no;;;0;0;;;;;0;0;0;0;;;;;;;;;/+SH/g;NoName;0;no;;;;;;;;;no;;;0;0;;;;;0;0;0;0;;;;;;;;;/+M/g;NoName;0;no;;;;;;;;;no;;;0;0;;;;;0;0;0;0;;;;;;;;;/']"/>
  <Column Name="H2S/g;NoName;0;no;;;;;;;;;no;;;0;0;;;;;0;0;0;0;;;;;;;;;/+M/g;NoName;0;no;;;;;;;;;no;;;0;0;;;;;0;0;0;0;;;;;;;;;/&lt;=&gt;H/g;NoName;0;no;;;;;;;;;no;;;0;0;;;;;0;0;0;0;;;;;;;;;/+SH/g;NoName;0;no;;;;;;;;;no;;;0;0;;;;;0;0;0;0;;;;;;;;;/+M/g;NoName;0;no;;;;;;;;;no;;;0;0;;;;;0;0;0;0;;;;;;;;;/" Role="reaction_enthalpy" Link="//ChemicalProcess[@Name='H2S/g;NoName;0;no;;;;;;;;;no;;;0;0;;;;;0;0;0;0;;;;;;;;;/+M/g;NoName;0;no;;;;;;;;;no;;;0;0;;;;;0;0;0;0;;;;;;;;;/&lt;=&gt;H/g;NoName;0;no;;;;;;;;;no;;;0;0;;;;;0;0;0;0;;;;;;;;;/+SH/g;NoName;0;no;;;;;;;;;no;;;0;0;;;;;0;0;0;0;;;;;;;;;/+M/g;NoName;0;no;;;;;;;;;no;;;0;0;;;;;0;0;0;0;;;;;;;;;/']"/>
  <Column Name="S/g;NoName;0;no;;;;;;;;;no;;;0;0;;;;;0;0;0;0;;;;;;;;;/+H2S/g;NoName;0;no;;;;;;;;;no;;;0;0;;;;;0;0;0;0;;;;;;;;;/&lt;=&gt;H2/g;NoName;0;no;;;;;;;;;no;;;0;0;;;;;0;0;0;0;;;;;;;;;/+S2/g;NoName;0;no;;;;;;;;;no;;;0;0;;;;;0;0;0;0;;;;;;;;;/" Role="rate_direct" Link="//ChemicalProcess[@Name='S/g;NoName;0;no;;;;;;;;;no;;;0;0;;;;;0;0;0;0;;;;;;;;;/+H2S/g;NoName;0;no;;;;;;;;;no;;;0;0;;;;;0;0;0;0;;;;;;;;;/&lt;=&gt;H2/g;NoName;0;no;;;;;;;;;no;;;0;0;;;;;0;0;0;0;;;;;;;;;/+S2/g;NoName;0;no;;;;;;;;;no;;;0;0;;;;;0;0;0;0;;;;;;;;;/']"/>
  <Column Name="S/g;NoName;0;no;;;;;;;;;no;;;0;0;;;;;0;0;0;0;;;;;;;;;/+H2S/g;NoName;0;no;;;;;;;;;no;;;0;0;;;;;0;0;0;0;;;;;;;;;/&lt;=&gt;H2/g;NoName;0;no;;;;;;;;;no;;;0;0;;;;;0;0;0;0;;;;;;;;;/+S2/g;NoName;0;no;;;;;;;;;no;;;0;0;;;;;0;0;0;0;;;;;;;;;/" Role="rate_reverse" Link="//ChemicalProcess[@Name='S/g;NoName;0;no;;;;;;;;;no;;;0;0;;;;;0;0;0;0;;;;;;;;;/+H2S/g;NoName;0;no;;;;;;;;;no;;;0;0;;;;;0;0;0;0;;;;;;;;;/&lt;=&gt;H2/g;NoName;0;no;;;;;;;;;no;;;0;0;;;;;0;0;0;0;;;;;;;;;/+S2/g;NoName;0;no;;;;;;;;;no;;;0;0;;;;;0;0;0;0;;;;;;;;;/']"/>
  <Column Name="S/g;NoName;0;no;;;;;;;;;no;;;0;0;;;;;0;0;0;0;;;;;;;;;/+H2S/g;NoName;0;no;;;;;;;;;no;;;0;0;;;;;0;0;0;0;;;;;;;;;/&lt;=&gt;H2/g;NoName;0;no;;;;;;;;;no;;;0;0;;;;;0;0;0;0;;;;;;;;;/+S2/g;NoName;0;no;;;;;;;;;no;;;0;0;;;;;0;0;0;0;;;;;;;;;/" Role="rate" Link="//ChemicalProcess[@Name='S/g;NoName;0;no;;;;;;;;;no;;;0;0;;;;;0;0;0;0;;;;;;;;;/+H2S/g;NoName;0;no;;;;;;;;;no;;;0;0;;;;;0;0;0;0;;;;;;;;;/&lt;=&gt;H2/g;NoName;0;no;;;;;;;;;no;;;0;0;;;;;0;0;0;0;;;;;;;;;/+S2/g;NoName;0;no;;;;;;;;;no;;;0;0;;;;;0;0;0;0;;;;;;;;;/']"/>
  <Column Name="S/g;NoName;0;no;;;;;;;;;no;;;0;0;;;;;0;0;0;0;;;;;;;;;/+H2S/g;NoName;0;no;;;;;;;;;no;;;0;0;;;;;0;0;0;0;;;;;;;;;/&lt;=&gt;H2/g;NoName;0;no;;;;;;;;;no;;;0;0;;;;;0;0;0;0;;;;;;;;;/+S2/g;NoName;0;no;;;;;;;;;no;;;0;0;;;;;0;0;0;0;;;;;;;;;/" Role="reaction_enthalpy" Link="//ChemicalProcess[@Name='S/g;NoName;0;no;;;;;;;;;no;;;0;0;;;;;0;0;0;0;;;;;;;;;/+H2S/g;NoName;0;no;;;;;;;;;no;;;0;0;;;;;0;0;0;0;;;;;;;;;/&lt;=&gt;H2/g;NoName;0;no;;;;;;;;;no;;;0;0;;;;;0;0;0;0;;;;;;;;;/+S2/g;NoName;0;no;;;;;;;;;no;;;0;0;;;;;0;0;0;0;;;;;;;;;/']"/>
  <Column Name="SH/g;NoName;0;no;;;;;;;;;no;;;0;0;;;;;0;0;0;0;;;;;;;;;/+SH/g;NoName;0;no;;;;;;;;;no;;;0;0;;;;;0;0;0;0;;;;;;;;;/&lt;=&gt;H2/g;NoName;0;no;;;;;;;;;no;;;0;0;;;;;0;0;0;0;;;;;;;;;/+S2/g;NoName;0;no;;;;;;;;;no;;;0;0;;;;;0;0;0;0;;;;;;;;;/" Role="rate_direct" Link="//ChemicalProcess[@Name='SH/g;NoName;0;no;;;;;;;;;no;;;0;0;;;;;0;0;0;0;;;;;;;;;/+SH/g;NoName;0;no;;;;;;;;;no;;;0;0;;;;;0;0;0;0;;;;;;;;;/&lt;=&gt;H2/g;NoName;0;no;;;;;;;;;no;;;0;0;;;;;0;0;0;0;;;;;;;;;/+S2/g;NoName;0;no;;;;;;;;;no;;;0;0;;;;;0;0;0;0;;;;;;;;;/']"/>
  <Column Name="SH/g;NoName;0;no;;;;;;;;;no;;;0;0;;;;;0;0;0;0;;;;;;;;;/+SH/g;NoName;0;no;;;;;;;;;no;;;0;0;;;;;0;0;0;0;;;;;;;;;/&lt;=&gt;H2/g;NoName;0;no;;;;;;;;;no;;;0;0;;;;;0;0;0;0;;;;;;;;;/+S2/g;NoName;0;no;;;;;;;;;no;;;0;0;;;;;0;0;0;0;;;;;;;;;/" Role="rate_reverse" Link="//ChemicalProcess[@Name='SH/g;NoName;0;no;;;;;;;;;no;;;0;0;;;;;0;0;0;0;;;;;;;;;/+SH/g;NoName;0;no;;;;;;;;;no;;;0;0;;;;;0;0;0;0;;;;;;;;;/&lt;=&gt;H2/g;NoName;0;no;;;;;;;;;no;;;0;0;;;;;0;0;0;0;;;;;;;;;/+S2/g;NoName;0;no;;;;;;;;;no;;;0;0;;;;;0;0;0;0;;;;;;;;;/']"/>
  <Column Name="SH/g;NoName;0;no;;;;;;;;;no;;;0;0;;;;;0;0;0;0;;;;;;;;;/+SH/g;NoName;0;no;;;;;;;;;no;;;0;0;;;;;0;0;0;0;;;;;;;;;/&lt;=&gt;H2/g;NoName;0;no;;;;;;;;;no;;;0;0;;;;;0;0;0;0;;;;;;;;;/+S2/g;NoName;0;no;;;;;;;;;no;;;0;0;;;;;0;0;0;0;;;;;;;;;/" Role="rate" Link="//ChemicalProcess[@Name='SH/g;NoName;0;no;;;;;;;;;no;;;0;0;;;;;0;0;0;0;;;;;;;;;/+SH/g;NoName;0;no;;;;;;;;;no;;;0;0;;;;;0;0;0;0;;;;;;;;;/&lt;=&gt;H2/g;NoName;0;no;;;;;;;;;no;;;0;0;;;;;0;0;0;0;;;;;;;;;/+S2/g;NoName;0;no;;;;;;;;;no;;;0;0;;;;;0;0;0;0;;;;;;;;;/']"/>
  <Column Name="SH/g;NoName;0;no;;;;;;;;;no;;;0;0;;;;;0;0;0;0;;;;;;;;;/+SH/g;NoName;0;no;;;;;;;;;no;;;0;0;;;;;0;0;0;0;;;;;;;;;/&lt;=&gt;H2/g;NoName;0;no;;;;;;;;;no;;;0;0;;;;;0;0;0;0;;;;;;;;;/+S2/g;NoName;0;no;;;;;;;;;no;;;0;0;;;;;0;0;0;0;;;;;;;;;/" Role="reaction_enthalpy" Link="//ChemicalProcess[@Name='SH/g;NoName;0;no;;;;;;;;;no;;;0;0;;;;;0;0;0;0;;;;;;;;;/+SH/g;NoName;0;no;;;;;;;;;no;;;0;0;;;;;0;0;0;0;;;;;;;;;/&lt;=&gt;H2/g;NoName;0;no;;;;;;;;;no;;;0;0;;;;;0;0;0;0;;;;;;;;;/+S2/g;NoName;0;no;;;;;;;;;no;;;0;0;;;;;0;0;0;0;;;;;;;;;/']"/>
  <Column Name="S2/g;NoName;0;no;;;;;;;;;no;;;0;0;;;;;0;0;0;0;;;;;;;;;/+S2/g;NoName;0;no;;;;;;;;;no;;;0;0;;;;;0;0;0;0;;;;;;;;;/+M/g;NoName;0;no;;;;;;;;;no;;;0;0;;;;;0;0;0;0;;;;;;;;;/&lt;=&gt;S4/g;NoName;0;no;;;;;;;;;no;;;0;0;;;;;0;0;0;0;;;;;;;;;/+M/g;NoName;0;no;;;;;;;;;no;;;0;0;;;;;0;0;0;0;;;;;;;;;/" Role="rate_direct" Link="//ChemicalProcess[@Name='S2/g;NoName;0;no;;;;;;;;;no;;;0;0;;;;;0;0;0;0;;;;;;;;;/+S2/g;NoName;0;no;;;;;;;;;no;;;0;0;;;;;0;0;0;0;;;;;;;;;/+M/g;NoName;0;no;;;;;;;;;no;;;0;0;;;;;0;0;0;0;;;;;;;;;/&lt;=&gt;S4/g;NoName;0;no;;;;;;;;;no;;;0;0;;;;;0;0;0;0;;;;;;;;;/+M/g;NoName;0;no;;;;;;;;;no;;;0;0;;;;;0;0;0;0;;;;;;;;;/']"/>
  <Column Name="S2/g;NoName;0;no;;;;;;;;;no;;;0;0;;;;;0;0;0;0;;;;;;;;;/+S2/g;NoName;0;no;;;;;;;;;no;;;0;0;;;;;0;0;0;0;;;;;;;;;/+M/g;NoName;0;no;;;;;;;;;no;;;0;0;;;;;0;0;0;0;;;;;;;;;/&lt;=&gt;S4/g;NoName;0;no;;;;;;;;;no;;;0;0;;;;;0;0;0;0;;;;;;;;;/+M/g;NoName;0;no;;;;;;;;;no;;;0;0;;;;;0;0;0;0;;;;;;;;;/" Role="rate_reverse" Link="//ChemicalProcess[@Name='S2/g;NoName;0;no;;;;;;;;;no;;;0;0;;;;;0;0;0;0;;;;;;;;;/+S2/g;NoName;0;no;;;;;;;;;no;;;0;0;;;;;0;0;0;0;;;;;;;;;/+M/g;NoName;0;no;;;;;;;;;no;;;0;0;;;;;0;0;0;0;;;;;;;;;/&lt;=&gt;S4/g;NoName;0;no;;;;;;;;;no;;;0;0;;;;;0;0;0;0;;;;;;;;;/+M/g;NoName;0;no;;;;;;;;;no;;;0;0;;;;;0;0;0;0;;;;;;;;;/']"/>
  <Column Name="S2/g;NoName;0;no;;;;;;;;;no;;;0;0;;;;;0;0;0;0;;;;;;;;;/+S2/g;NoName;0;no;;;;;;;;;no;;;0;0;;;;;0;0;0;0;;;;;;;;;/+M/g;NoName;0;no;;;;;;;;;no;;;0;0;;;;;0;0;0;0;;;;;;;;;/&lt;=&gt;S4/g;NoName;0;no;;;;;;;;;no;;;0;0;;;;;0;0;0;0;;;;;;;;;/+M/g;NoName;0;no;;;;;;;;;no;;;0;0;;;;;0;0;0;0;;;;;;;;;/" Role="rate" Link="//ChemicalProcess[@Name='S2/g;NoName;0;no;;;;;;;;;no;;;0;0;;;;;0;0;0;0;;;;;;;;;/+S2/g;NoName;0;no;;;;;;;;;no;;;0;0;;;;;0;0;0;0;;;;;;;;;/+M/g;NoName;0;no;;;;;;;;;no;;;0;0;;;;;0;0;0;0;;;;;;;;;/&lt;=&gt;S4/g;NoName;0;no;;;;;;;;;no;;;0;0;;;;;0;0;0;0;;;;;;;;;/+M/g;NoName;0;no;;;;;;;;;no;;;0;0;;;;;0;0;0;0;;;;;;;;;/']"/>
  <Column Name="S2/g;NoName;0;no;;;;;;;;;no;;;0;0;;;;;0;0;0;0;;;;;;;;;/+S2/g;NoName;0;no;;;;;;;;;no;;;0;0;;;;;0;0;0;0;;;;;;;;;/+M/g;NoName;0;no;;;;;;;;;no;;;0;0;;;;;0;0;0;0;;;;;;;;;/&lt;=&gt;S4/g;NoName;0;no;;;;;;;;;no;;;0;0;;;;;0;0;0;0;;;;;;;;;/+M/g;NoName;0;no;;;;;;;;;no;;;0;0;;;;;0;0;0;0;;;;;;;;;/" Role="reaction_enthalpy" Link="//ChemicalProcess[@Name='S2/g;NoName;0;no;;;;;;;;;no;;;0;0;;;;;0;0;0;0;;;;;;;;;/+S2/g;NoName;0;no;;;;;;;;;no;;;0;0;;;;;0;0;0;0;;;;;;;;;/+M/g;NoName;0;no;;;;;;;;;no;;;0;0;;;;;0;0;0;0;;;;;;;;;/&lt;=&gt;S4/g;NoName;0;no;;;;;;;;;no;;;0;0;;;;;0;0;0;0;;;;;;;;;/+M/g;NoName;0;no;;;;;;;;;no;;;0;0;;;;;0;0;0;0;;;;;;;;;/']"/>
</TblDescription>
